fayouts/__init__.py
fayouts/aiobot/startproject.py
fayouts/calc/calc.py
fayouts/datetime/datetime.py
fayouts/datetime/dt.py
fayouts/discobot/startproject.py
fayouts/fayouts/__init__.py
fayouts/fayouts/main.py
fayouts/files/files.py
fayouts/start/newproject.py
fayouts-1.1.0.dist-info/WHEEL
fayouts-1.1.0.dist-info/METADATA
fayouts-1.1.0.dist-info/RECORD
