Metadata-Version: 2.1
Name: fayouts
Version: 1.1.0
Summary: Fayouts can do a lot, but they are just a tool
Author: Fakem1ner
Author-email: 87234992+Fakeminer@users.noreply.github.com
Requires-Python: >=3.6,<4.0
Classifier: Programming Language :: Python :: 3
Classifier: Programming Language :: Python :: 3.10
Classifier: Programming Language :: Python :: 3.6
Classifier: Programming Language :: Python :: 3.7
Classifier: Programming Language :: Python :: 3.8
Classifier: Programming Language :: Python :: 3.9
